Metadata-Version: 2.1
Name: ravand-plotting
Version: 1.0.0
Summary: Plotting package for Backtrader (Bokeh)
Home-page: https://github.com/coci/ravand_plot
Author: soroush
Author-email: soroush_safarii@yahoo.com
License: GPLv3+
Keywords: trading,development,plotting,backtrader
Platform: UNKNOWN
Requires-Python: >=3.6
